hexout.py
hexout-0.1.0.dist-info/entry_points.txt
hexout-0.1.0.dist-info/LICENSE
hexout-0.1.0.dist-info/WHEEL
hexout-0.1.0.dist-info/METADATA
hexout-0.1.0.dist-info/RECORD
