Metadata-Version: 2.1
Name: hexout
Version: 0.1.0
Summary: A brief description of your package.
License: MIT
Author: Your Name
Author-email: youremail@example.com
Requires-Python: >=3.12,<4.0
Classifier: License :: OSI Approved :: MIT License
Classifier: Programming Language :: Python :: 3
